arkham_solver/__init__.py
arkham_solver/client.py
arkham_solver/constants.py
arkham_solver/exceptions.py
arkham_solver/models.py
arkham_solver/presets.py
arkham_solver-0.2.4.dist-info/METADATA
arkham_solver-0.2.4.dist-info/WHEEL
arkham_solver-0.2.4.dist-info/top_level.txt
arkham_solver-0.2.4.dist-info/RECORD
